{"features": {"height": 52.130067567567565, "max_width": 26.50618087182824}, "internal": {"px_width_in_mm": 0.04554326610279766, "px_height_in_mm": 0.04560810810810811, "paper_roi": {"horiz": {"corner": 562, "length": 4242}, "vert": {"corner": 1711, "length": 6213}}, "height_segment": {"corner": 4222, "length": 1143}, "widths": [{"corner": 2705, "length": 3}, {"corner": 2649, "length": 162}, {"corner": 2587, "length": 309}, {"corner": 2521, "length": 445}, {"corner": 2458, "length": 549}, {"corner": 2433, "length": 572}, {"corner": 2448, "length": 548}, {"corner": 2464, "length": 503}, {"corner": 2503, "length": 393}, {"corner": 2599, "length": 186}, {"corner": 2711, "length": 15}], "max_width": {"corner": 2431, "length": 582}}}