{"features": {"height": 71.81796226415095, "max_width": 35.4585798816568}, "internal": {"px_width_in_mm": 0.04437869822485207, "px_height_in_mm": 0.044830188679245285, "paper_roi": {"horiz": {"corner": 284, "length": 4383}, "vert": {"corner": 1037, "length": 6351}}, "height_segment": {"corner": 4054, "length": 1602}, "widths": [{"corner": 2262, "length": 9}, {"corner": 2122, "length": 372}, {"corner": 2077, "length": 488}, {"corner": 2055, "length": 575}, {"corner": 2078, "length": 572}, {"corner": 2130, "length": 507}, {"corner": 2308, "length": 161}, {"corner": 2428, "length": 31}, {"corner": 2513, "length": 34}, {"corner": 2617, "length": 42}, {"corner": 2814, "length": 4}], "max_width": {"corner": 2053, "length": 799}}}