{"features": {"height": 80.56608478802993, "max_width": 37.9291553133515, "width_0perc": 0.004310344827586207, "width_10perc": 0.2521551724137931, "width_20perc": 0.584051724137931, "width_30perc": 0.7952586206896551, "width_40perc": 0.9331896551724138, "width_50perc": 0.9870689655172413, "width_60perc": 0.9762931034482759, "width_70perc": 0.8793103448275862, "width_80perc": 0.7025862068965517, "width_90perc": 0.4353448275862069, "width_100perc": 0.0668103448275862, "avg_color_hue": 32.81806020505523, "avg_color_sat": 168.53654698007483, "avg_color_val": 30.338626385696628}, "internal": {"px_width_in_mm": 0.08174386920980926, "px_height_in_mm": 0.08229426433915212, "paper_roi": {"horiz": {"corner": 276, "length": 2422}, "vert": {"corner": 310, "length": 3467}}, "height_segment": {"corner": 1425, "length": 979}, "widths": [{"corner": 1511, "length": 2}, {"corner": 1436, "length": 117}, {"corner": 1356, "length": 271}, {"corner": 1309, "length": 369}, {"corner": 1282, "length": 433}, {"corner": 1273, "length": 458}, {"corner": 1282, "length": 453}, {"corner": 1312, "length": 408}, {"corner": 1357, "length": 326}, {"corner": 1421, "length": 202}, {"corner": 1512, "length": 31}], "max_width": {"corner": 1273, "length": 464}}}